abx_plugin_npm/__init__.py
abx_plugin_npm/binaries.py
abx_plugin_npm/binproviders.py
abx_plugin_npm/config.py
abx_plugin_npm-2024.10.24.dist-info/METADATA
abx_plugin_npm-2024.10.24.dist-info/WHEEL
abx_plugin_npm-2024.10.24.dist-info/entry_points.txt
abx_plugin_npm-2024.10.24.dist-info/RECORD
